[
  {
    "slug": "halo-the-master-chief-collection",
    "name": "Halo: The Master Chief Collection",
    "description": "The definitive collection of the Halo series, featuring remastered versions of several titles in the iconic franchise.",
    "versions": [
      {
        "platform": "Windows",
        "url": "https://1fichier.com/?swr3dppkim0f0jlo3ax8",
        "tags": [
          "Shooter",
          "Sci-Fi",
          "Singleplayer/Multiplayer"
        ]
      }
    ]
  },
  {
    "slug": "watch-dogs-legion",
    "name": "Watch Dogs: Legion",
    "description": "Build a resistance from virtually anyone you see as you hack, infiltrate, and fight to take back a near-future London that is facing its downfall.",
    "versions": [
      {
        "platform": "Windows",
        "url": "https://www.filecrypt.cc/Container/AF48548052",
        "tags": [
          "Action",
          "Open World",
          "Stealth"
        ]
      }
    ]
  },
  {
    "slug": "sleeping-dogs",
    "name": "Sleeping Dogs",
    "description": "An open-world action-adventure set in Hong Kong, following an undercover cop's journey into the Sun On Yee Triad.",
    "versions": [
      {
        "platform": "Windows",
        "url": "https://buzzheavier.com/jgglyhqzkaqu",
        "tags": [
          "Action",
          "Open World",
          "Martial Arts"
        ]
      }
    ]
  },
  {
    "slug": "saints-row-2",
    "name": "Saints Row 2",
    "description": "Rebuild the Saints and take back Stilwater in this open-world sandbox known for its blend of grit and over-the-top action.",
    "versions": [
      {
        "platform": "Windows",
        "url": "https://gofile.io/d/1vSGdc",
        "tags": [
          "Action",
          "Open World",
          "Crime"
        ]
      }
    ]
  },
  {
    "slug": "saints-row-the-third-remastered",
    "name": "Saints Row: The Third Remastered",
    "description": "The definitive version of the Third Street Saints' rise to power, featuring enhanced graphics and all DLC.",
    "versions": [
      {
        "platform": "Windows",
        "url": "https://buzzheavier.com/sbvfnnkivkmy",
        "tags": [
          "Action",
          "Open World",
          "Comedy"
        ]
      }
    ]
  },
  {
    "slug": "saints-row-iv-re-elected",
    "name": "Saints Row IV: Re-Elected",
    "description": "The President of the United States must save Earth from an alien invasion using superpowers and strange weaponry.",
    "versions": [
      {
        "platform": "Windows",
        "url": "https://megadb.net/8ben92npd4hl",
        "tags": [
          "Action",
          "Open World",
          "Sci-Fi"
        ]
      }
    ]
  },
  {
    "slug": "saints-row-reboot",
    "name": "Saints Row (Reboot)",
    "description": "A fresh start for the series set in the vibrant city of Santo Ileso, focusing on the birth of a new criminal empire.",
    "versions": [
      {
        "platform": "Windows",
        "url": "https://gofile.io/d/YnMg0v",
        "tags": [
          "Action",
          "Open World",
          "Crime"
        ]
      }
    ]
  },
  {
    "slug": "left-4-dead",
    "name": "Left 4 Dead",
    "description": "A cooperative first-person shooter where survivors must fight through hordes of zombies to reach safety.",
    "versions": [
      {
        "platform": "Windows",
        "url": "https://megadb.net/5ocsgftd87pp",
        "tags": [
          "Shooter",
          "Horror",
          "Co-op"
        ]
      }
    ]
  },
  {
    "slug": "left-4-dead-2",
    "name": "Left 4 Dead 2",
    "description": "The sequel to the hit co-op horror FPS, adding new characters, infected types, and melee weapons.",
    "versions": [
      {
        "platform": "Windows",
        "url": "https://gofile.io/d/RPbTag",
        "tags": [
          "Shooter",
          "Horror",
          "Co-op"
        ]
      }
    ]
  },
  {
    "slug": "horizon-zero-dawn",
    "name": "Horizon Zero Dawn",
    "description": "In an era where Machines roam the land and mankind is no longer the dominant species, a young hunter named Aloy embarks on a journey to discover her destiny.",
    "versions": [
      {
        "platform": "Windows",
        "url": "https://www.filecrypt.cc/Container/FD60075769",
        "tags": [
          "Action",
          "RPG",
          "Open World"
        ]
      }
    ]
  },
  {
    "slug": "fifa-14",
    "name": "FIFA 14",
    "description": "Experience the emotion of scoring great goals with realistic ball physics and authentic stadium atmospheres.",
    "versions": [
      {
        "platform": "Windows",
        "url": "https://buzzheavier.com/9eqbv6yp6136",
        "tags": [
          "Sports",
          "Football",
          "Singleplayer/Multiplayer"
        ]
      }
    ]
  },
  {
    "slug": "fifa-16",
    "name": "FIFA 16",
    "description": "Innovating across the entire pitch, delivering a balanced, authentic, and exciting football experience.",
    "versions": [
      {
        "platform": "Windows",
        "url": "https://gofile.io/d/7CQ62z",
        "tags": [
          "Sports",
          "Football",
          "Singleplayer/Multiplayer"
        ]
      }
    ]
  },
  {
    "slug": "fifa-17",
    "name": "FIFA 17",
    "description": "Powered by Frostbite, introducing 'The Journey' story mode and transformed physical play.",
    "versions": [
      {
        "platform": "Windows",
        "url": "https://gofile.io/d/tH5xhL",
        "tags": [
          "Sports",
          "Football",
          "Simulation"
        ]
      }
    ]
  },
  {
    "slug": "fifa-20",
    "name": "FIFA 20",
    "description": "Breaking new ground with the VOLTA Football street mode and overhauled ball motion mechanics.",
    "versions": [
      {
        "platform": "Windows",
        "url": "https://gofile.io/d/ZrML6w",
        "tags": [
          "Sports",
          "Football",
          "Singleplayer/Multiplayer"
        ]
      }
    ]
  },
  {
    "slug": "fifa-21",
    "name": "FIFA 21",
    "description": "Win as one in FIFA 21 with new ways to team up and express yourself on the street and in the stadium.",
    "versions": [
      {
        "platform": "Windows",
        "url": "https://gofile.io/d/d2zcN5",
        "tags": [
          "Sports",
          "Football",
          "Simulation"
        ]
      }
    ]
  },
  {
    "slug": "fifa-23",
    "name": "FIFA 23",
    "description": "The final EA Sports FIFA title, featuring HyperMotion2 Technology and both men's and women's World Cup modes.",
    "versions": [
      {
        "platform": "Windows",
        "url": "https://buzzheavier.com/zmasjuexf733",
        "tags": [
          "Sports",
          "Football",
          "Singleplayer/Multiplayer"
        ]
      }
    ]
  }
]
